palzlib/__init__.py
palzlib/database/__init__.py
palzlib/database/db_client.py
palzlib/database/db_config.py
palzlib/database/db_mapping.py
palzlib/sentiment_analyzers/__init__.py
palzlib/sentiment_analyzers/langs/__init__.py
palzlib/sentiment_analyzers/langs/dan/__init__.py
palzlib/sentiment_analyzers/langs/dan/sentiment_analyzer.py
palzlib/sentiment_analyzers/langs/eng/__init__.py
palzlib/sentiment_analyzers/langs/eng/sentiment_analyzer.py
palzlib/sentiment_analyzers/langs/hun/__init__.py
palzlib/sentiment_analyzers/langs/hun/emotion_analyzer.py
palzlib/sentiment_analyzers/langs/hun/sentiment_analyzer.py
palzlib/sentiment_analyzers/models.py
palzlib-0.1.3.dist-info/METADATA
palzlib-0.1.3.dist-info/WHEEL
palzlib-0.1.3.dist-info/RECORD
